podium/__init__.py
podium/field.py
podium/vocab.py
podium/datasets/__init__.py
podium/datasets/arrow.py
podium/datasets/dataset.py
podium/datasets/example_factory.py
podium/datasets/hf.py
podium/datasets/hierarhical_dataset.py
podium/datasets/iterator.py
podium/datasets/tabular_dataset.py
podium/datasets/impl/__init__.py
podium/datasets/impl/conllu_dataset.py
podium/datasets/impl/cornell_movie_dialogs.py
podium/datasets/impl/imdb.py
podium/datasets/impl/iris.py
podium/datasets/impl/snli.py
podium/datasets/impl/sst.py
podium/experimental/__init__.py
podium/experimental/model_selection/__init__.py
podium/experimental/model_selection/model_selection.py
podium/experimental/models/__init__.py
podium/experimental/models/batch_transform_functions.py
podium/experimental/models/experiment.py
podium/experimental/models/model.py
podium/experimental/models/trainer.py
podium/experimental/models/transformers.py
podium/experimental/models/impl/__init__.py
podium/experimental/models/impl/blcc_model.py
podium/experimental/models/impl/fc_model.py
podium/experimental/models/impl/simple_trainers.py
podium/experimental/models/impl/svm_model.py
podium/experimental/models/impl/blcc/__init__.py
podium/experimental/models/impl/blcc/chain_crf.py
podium/experimental/models/impl/eurovoc_models/__init__.py
podium/experimental/models/impl/eurovoc_models/multilabel_svm.py
podium/experimental/models/impl/pytorch/__init__.py
podium/experimental/models/impl/pytorch/models.py
podium/experimental/models/impl/pytorch/sequence_classification.py
podium/experimental/models/impl/pytorch/trainers.py
podium/experimental/pipeline/__init__.py
podium/experimental/pipeline/pipeline.py
podium/experimental/validation/__init__.py
podium/experimental/validation/validation.py
podium/preproc/__init__.py
podium/preproc/hooks.py
podium/preproc/sentencizers.py
podium/preproc/tokenizers.py
podium/storage/__init__.py
podium/storage/resources/__init__.py
podium/storage/resources/downloader.py
podium_nlp-0.1.1.dist-info/LICENSE
podium_nlp-0.1.1.dist-info/METADATA
podium_nlp-0.1.1.dist-info/WHEEL
podium_nlp-0.1.1.dist-info/top_level.txt
podium_nlp-0.1.1.dist-info/RECORD
